source_iterable/__init__.py
source_iterable/components.py
source_iterable/manifest.yaml
source_iterable/run.py
source_iterable/schemas/campaigns.json
source_iterable/schemas/campaigns_metrics.json
source_iterable/schemas/channels.json
source_iterable/schemas/email_bounce.json
source_iterable/schemas/email_click.json
source_iterable/schemas/email_complaint.json
source_iterable/schemas/email_open.json
source_iterable/schemas/email_send.json
source_iterable/schemas/email_send_skip.json
source_iterable/schemas/email_subscribe.json
source_iterable/schemas/email_unsubscribe.json
source_iterable/schemas/events.json
source_iterable/schemas/list_users.json
source_iterable/schemas/lists.json
source_iterable/schemas/message_types.json
source_iterable/schemas/metadata.json
source_iterable/schemas/templates.json
source_iterable/schemas/users.json
source_iterable/slice_generators.py
source_iterable/source.py
source_iterable/spec.json
source_iterable/streams.py
source_iterable/utils.py
airbyte_source_iterable-0.6.53.dist-info/METADATA
airbyte_source_iterable-0.6.53.dist-info/WHEEL
airbyte_source_iterable-0.6.53.dist-info/entry_points.txt
airbyte_source_iterable-0.6.53.dist-info/RECORD
