Metadata-Version: 2.1
Name: airbyte-source-iterable
Version: 0.6.53
Summary: Source implementation for Iterable.
Home-page: https://airbyte.com
License: ELv2
Author: Airbyte
Author-email: contact@airbyte.io
Requires-Python: >=3.9,<3.12
Classifier: License :: Other/Proprietary License
Classifier: Programming Language :: Python :: 3
Classifier: Programming Language :: Python :: 3.9
Classifier: Programming Language :: Python :: 3.10
Classifier: Programming Language :: Python :: 3.11
Requires-Dist: airbyte-cdk (>=3,<4)
Requires-Dist: pendulum (==2.1.2)
Requires-Dist: python-dateutil (==2.8.2)
Project-URL: Documentation, https://docs.airbyte.com/integrations/sources/iterable
Project-URL: Repository, https://github.com/airbytehq/airbyte
